{"expireTime":9007200865668482000,"key":"b105734202b627b38bc0714b81e2d05e","val":{"name":"IMAGE_PROCESSING","inputPaths":["/Users/victor/Documents/git_clone/PortFolio/src/images/section3/Screenshot 2021-01-18 at 00.51.02.png"],"outputDir":"/Users/victor/Documents/git_clone/PortFolio/public/static/f776b5c87d0fd37f2cb56a88ad3b8ccb","args":{"isLazy":false,"operations":[{"outputPath":"497c6/Screenshot 2021-01-18 at 00.51.02.png","args":{"width":400,"cropFocus":17,"toFormat":"png","fit":"cover","background":"rgba(0,0,0,1)"}},{"outputPath":"ee604/Screenshot 2021-01-18 at 00.51.02.png","args":{"width":800,"cropFocus":17,"toFormat":"png","fit":"cover","background":"rgba(0,0,0,1)"}},{"outputPath":"5707d/Screenshot 2021-01-18 at 00.51.02.png","args":{"width":1600,"cropFocus":17,"toFormat":"png","fit":"cover","background":"rgba(0,0,0,1)"}},{"outputPath":"2588d/Screenshot 2021-01-18 at 00.51.02.png","args":{"width":1844,"cropFocus":17,"toFormat":"png","fit":"cover","background":"rgba(0,0,0,1)"}}],"pluginOptions":{"base64Width":20,"forceBase64Format":"","useMozJpeg":false,"stripMetadata":true,"lazyImageGeneration":true,"defaultQuality":50,"failOnError":true,"plugins":[]}}}}